lightdash_ai_tools/__init__.py
lightdash_ai_tools/common/__init__.py
lightdash_ai_tools/common/tools/__init__.py
lightdash_ai_tools/common/tools/get_explore.py
lightdash_ai_tools/common/tools/get_explores.py
lightdash_ai_tools/common/tools/get_group.py
lightdash_ai_tools/common/tools/get_groups_in_organization.py
lightdash_ai_tools/common/tools/get_organization_members.py
lightdash_ai_tools/common/tools/get_project.py
lightdash_ai_tools/common/tools/get_project_members.py
lightdash_ai_tools/common/tools/get_projects.py
lightdash_ai_tools/common/tools/get_spaces_in_project.py
lightdash_ai_tools/crewai/__init__.py
lightdash_ai_tools/crewai/tools/__init__.py
lightdash_ai_tools/crewai/tools/get_projects.py
lightdash_ai_tools/langchain/__init__.py
lightdash_ai_tools/langchain/tools/__init__.py
lightdash_ai_tools/langchain/tools/compile_query.py
lightdash_ai_tools/langchain/tools/get_explore.py
lightdash_ai_tools/langchain/tools/get_explores.py
lightdash_ai_tools/langchain/tools/get_group.py
lightdash_ai_tools/langchain/tools/get_groups_in_organization.py
lightdash_ai_tools/langchain/tools/get_organization_members.py
lightdash_ai_tools/langchain/tools/get_project.py
lightdash_ai_tools/langchain/tools/get_project_memgers.py
lightdash_ai_tools/langchain/tools/get_projects.py
lightdash_ai_tools/langchain/tools/get_spaces_in_project.py
lightdash_ai_tools/lightdash/__init__.py
lightdash_ai_tools/lightdash/client.py
lightdash_ai_tools/lightdash/api/__init__.py
lightdash_ai_tools/lightdash/api/base.py
lightdash_ai_tools/lightdash/api/compile_query_v1.py
lightdash_ai_tools/lightdash/api/get_explore_v1.py
lightdash_ai_tools/lightdash/api/get_explores_v1.py
lightdash_ai_tools/lightdash/api/get_group_v1.py
lightdash_ai_tools/lightdash/api/get_project_access_list_v1.py
lightdash_ai_tools/lightdash/api/get_project_v1.py
lightdash_ai_tools/lightdash/api/list_groups_in_organization_v1.py
lightdash_ai_tools/lightdash/api/list_organization_members_v1.py
lightdash_ai_tools-0.2.0.dist-info/METADATA
lightdash_ai_tools-0.2.0.dist-info/WHEEL
lightdash_ai_tools-0.2.0.dist-info/licenses/LICENSE
lightdash_ai_tools-0.2.0.dist-info/RECORD
