Metadata-Version: 2.4
Name: lightdash-ai-tools
Version: 0.2.0
Summary: AI tools for Lightdash
Author: yu-iskw
License:                                  Apache License
License-File: LICENSE
Classifier: Development Status :: 4 - Beta
Classifier: Intended Audience :: Information Technology
Classifier: Intended Audience :: System Administrators
Classifier: License :: OSI Approved :: Apache Software License
Classifier: Operating System :: OS Independent
Classifier: Programming Language :: Python
Classifier: Programming Language :: Python :: 3
Classifier: Programming Language :: Python :: 3 :: Only
Classifier: Programming Language :: Python :: 3.10
Classifier: Programming Language :: Python :: 3.11
Classifier: Programming Language :: Python :: 3.12
Classifier: Topic :: Software Development :: Libraries
Classifier: Topic :: Software Development :: Libraries :: Python Modules
Classifier: Typing :: Typed
Requires-Python: >=3.10.0
Requires-Dist: pydantic>=2.9
Requires-Dist: requests>=2.32
Provides-Extra: all
Requires-Dist: crewai[tools]<1.0,>=0.98.0; extra == 'all'
Requires-Dist: langchain-core<1.0,>=0.3; extra == 'all'
Provides-Extra: crewai
Requires-Dist: crewai[tools]<1.0,>=0.98.0; extra == 'crewai'
Provides-Extra: dev
Requires-Dist: build>=1.2.2.post1; extra == 'dev'
Requires-Dist: langchain-google-genai>=2.0.8; extra == 'dev'
Requires-Dist: langchain-google-vertexai>=2.0.7; extra == 'dev'
Requires-Dist: langchain-openai>=0.2.14; extra == 'dev'
Requires-Dist: langgraph>=0.2.61; extra == 'dev'
Requires-Dist: pytest<9.0,>=8.0; extra == 'dev'
Requires-Dist: python-dotenv<2.0.0,>=1.0.1; extra == 'dev'
Requires-Dist: ruff>=0.9.0; extra == 'dev'
Requires-Dist: streamlit<2.0.0,>=1.41.1; extra == 'dev'
Provides-Extra: langchain
Requires-Dist: langchain-core<1.0,>=0.3; extra == 'langchain'
